review_ipsum/__init__.py
review_ipsum/fixtures.py
review_ipsum/generator.py
review_ipsum-0.0.4.dist-info/METADATA
review_ipsum-0.0.4.dist-info/RECORD
review_ipsum-0.0.4.dist-info/WHEEL
review_ipsum-0.0.4.dist-info/top_level.txt
