Metadata-Version: 2.1
Name: review-ipsum
Version: 0.0.4
Summary: Review Themed Lorem Ipsum
Home-page: https://github.com/JakeBar/review-ipsum
Author: Jake Barber
Author-email: jake.b.dev@gmail.com
License: UNKNOWN
Platform: UNKNOWN
Classifier: Programming Language :: Python :: 2
Classifier: Programming Language :: Python :: 3
Classifier: License :: OSI Approved :: MIT License
Classifier: Operating System :: OS Independent
Classifier: Topic :: Utilities
